[{"arguments":["clang","-Wno-documentation-unknown-command","-Wno-unknown-warning-option","-Wno-unknown-pragmas","-nostdinc","-nostdinc++","-g","-std=gnu++11","-Wall","-Wextra","-Wextra","-fexceptions","-mthreads","-fsyntax-only","-m32","--target=i686-w64-mingw32","-DUNICODE","-D_UNICODE","-DWIN32","-DMINGW_HAS_SECURE_API","-DQT_DEPRECATED_WARNINGS","-DQT_QML_DEBUG","-DQT_NETWORK_LIB","-DQT_CORE_LIB","-DQ_CREATOR_RUN","-DQT_ANNOTATE_FUNCTION(x)=__attribute__((annotate(#x)))","-IF:\\QT\\Tools\\QtCreator\\share\\qtcreator\\cplusplus\\wrappedMingwHeaders","-IF:\\QT\\Tools\\QtCreator\\share\\qtcreator\\cplusplus\\wrappedQtHeaders","-IF:\\QT\\Tools\\QtCreator\\share\\qtcreator\\cplusplus\\wrappedQtHeaders\\QtCore","-ID:\\Desktop\\631\\firmware\\firmwareUpgrade","-IF:\\QT\\5.15.2\\mingw81_32\\include","-IF:\\QT\\5.15.2\\mingw81_32\\include\\QtNetwork","-IF:\\QT\\5.15.2\\mingw81_32\\include\\QtCore","-ID:\\Desktop\\631\\firmware\\build-firmwareUpgrade-Desktop_Qt_5_15_2_MinGW_32_bit-Debug\\debug","-ID:\\Desktop\\631\\firmware\\build-firmwareUpgrade-Desktop_Qt_5_15_2_MinGW_32_bit-Debug","-IF:\\QT\\5.15.2\\mingw81_32\\mkspecs\\win32-g++","-isystem","F:\\QT\\Tools\\mingw810_32\\lib\\gcc\\i686-w64-mingw32\\8.1.0\\include\\c++","-isystem","F:\\QT\\Tools\\mingw810_32\\lib\\gcc\\i686-w64-mingw32\\8.1.0\\include\\c++\\i686-w64-mingw32","-isystem","F:\\QT\\Tools\\mingw810_32\\lib\\gcc\\i686-w64-mingw32\\8.1.0\\include\\c++\\backward","-isystem","F:\\QT\\Tools\\QtCreator\\bin\\clang\\lib\\clang\\16\\include","-isystem","F:\\QT\\Tools\\mingw810_32\\i686-w64-mingw32\\include","-fmessage-length=0","-fdiagnostics-show-note-include-stack","-fretain-comments-from-system-headers","-fmacro-backtrace-limit=0","-ferror-limit=1000","-x","c++","D:\\Desktop\\631\\firmware\\firmwareUpgrade\\crc\\crc.cpp"],"directory":"D:/Desktop/631/firmware/build-firmwareUpgrade-Desktop_Qt_5_15_2_MinGW_32_bit-Debug/.qtc_clangd","file":"D:/Desktop/631/firmware/firmwareUpgrade/crc/crc.cpp"},{"arguments":["clang","-Wno-documentation-unknown-command","-Wno-unknown-warning-option","-Wno-unknown-pragmas","-nostdinc","-nostdinc++","-g","-std=gnu++11","-Wall","-Wextra","-Wextra","-fexceptions","-mthreads","-fsyntax-only","-m32","--target=i686-w64-mingw32","-DUNICODE","-D_UNICODE","-DWIN32","-DMINGW_HAS_SECURE_API","-DQT_DEPRECATED_WARNINGS","-DQT_QML_DEBUG","-DQT_NETWORK_LIB","-DQT_CORE_LIB","-DQ_CREATOR_RUN","-DQT_ANNOTATE_FUNCTION(x)=__attribute__((annotate(#x)))","-IF:\\QT\\Tools\\QtCreator\\share\\qtcreator\\cplusplus\\wrappedMingwHeaders","-IF:\\QT\\Tools\\QtCreator\\share\\qtcreator\\cplusplus\\wrappedQtHeaders","-IF:\\QT\\Tools\\QtCreator\\share\\qtcreator\\cplusplus\\wrappedQtHeaders\\QtCore","-ID:\\Desktop\\631\\firmware\\firmwareUpgrade","-IF:\\QT\\5.15.2\\mingw81_32\\include","-IF:\\QT\\5.15.2\\mingw81_32\\include\\QtNetwork","-IF:\\QT\\5.15.2\\mingw81_32\\include\\QtCore","-ID:\\Desktop\\631\\firmware\\build-firmwareUpgrade-Desktop_Qt_5_15_2_MinGW_32_bit-Debug\\debug","-ID:\\Desktop\\631\\firmware\\build-firmwareUpgrade-Desktop_Qt_5_15_2_MinGW_32_bit-Debug","-IF:\\QT\\5.15.2\\mingw81_32\\mkspecs\\win32-g++","-isystem","F:\\QT\\Tools\\mingw810_32\\lib\\gcc\\i686-w64-mingw32\\8.1.0\\include\\c++","-isystem","F:\\QT\\Tools\\mingw810_32\\lib\\gcc\\i686-w64-mingw32\\8.1.0\\include\\c++\\i686-w64-mingw32","-isystem","F:\\QT\\Tools\\mingw810_32\\lib\\gcc\\i686-w64-mingw32\\8.1.0\\include\\c++\\backward","-isystem","F:\\QT\\Tools\\QtCreator\\bin\\clang\\lib\\clang\\16\\include","-isystem","F:\\QT\\Tools\\mingw810_32\\i686-w64-mingw32\\include","-fmessage-length=0","-fdiagnostics-show-note-include-stack","-fretain-comments-from-system-headers","-fmacro-backtrace-limit=0","-ferror-limit=1000","-x","c++","D:\\Desktop\\631\\firmware\\firmwareUpgrade\\firmwareupgrade.cpp"],"directory":"D:/Desktop/631/firmware/build-firmwareUpgrade-Desktop_Qt_5_15_2_MinGW_32_bit-Debug/.qtc_clangd","file":"D:/Desktop/631/firmware/firmwareUpgrade/firmwareupgrade.cpp"},{"arguments":["clang","-Wno-documentation-unknown-command","-Wno-unknown-warning-option","-Wno-unknown-pragmas","-nostdinc","-nostdinc++","-g","-std=gnu++11","-Wall","-Wextra","-Wextra","-fexceptions","-mthreads","-fsyntax-only","-m32","--target=i686-w64-mingw32","-DUNICODE","-D_UNICODE","-DWIN32","-DMINGW_HAS_SECURE_API","-DQT_DEPRECATED_WARNINGS","-DQT_QML_DEBUG","-DQT_NETWORK_LIB","-DQT_CORE_LIB","-DQ_CREATOR_RUN","-DQT_ANNOTATE_FUNCTION(x)=__attribute__((annotate(#x)))","-IF:\\QT\\Tools\\QtCreator\\share\\qtcreator\\cplusplus\\wrappedMingwHeaders","-IF:\\QT\\Tools\\QtCreator\\share\\qtcreator\\cplusplus\\wrappedQtHeaders","-IF:\\QT\\Tools\\QtCreator\\share\\qtcreator\\cplusplus\\wrappedQtHeaders\\QtCore","-ID:\\Desktop\\631\\firmware\\firmwareUpgrade","-IF:\\QT\\5.15.2\\mingw81_32\\include","-IF:\\QT\\5.15.2\\mingw81_32\\include\\QtNetwork","-IF:\\QT\\5.15.2\\mingw81_32\\include\\QtCore","-ID:\\Desktop\\631\\firmware\\build-firmwareUpgrade-Desktop_Qt_5_15_2_MinGW_32_bit-Debug\\debug","-ID:\\Desktop\\631\\firmware\\build-firmwareUpgrade-Desktop_Qt_5_15_2_MinGW_32_bit-Debug","-IF:\\QT\\5.15.2\\mingw81_32\\mkspecs\\win32-g++","-isystem","F:\\QT\\Tools\\mingw810_32\\lib\\gcc\\i686-w64-mingw32\\8.1.0\\include\\c++","-isystem","F:\\QT\\Tools\\mingw810_32\\lib\\gcc\\i686-w64-mingw32\\8.1.0\\include\\c++\\i686-w64-mingw32","-isystem","F:\\QT\\Tools\\mingw810_32\\lib\\gcc\\i686-w64-mingw32\\8.1.0\\include\\c++\\backward","-isystem","F:\\QT\\Tools\\QtCreator\\bin\\clang\\lib\\clang\\16\\include","-isystem","F:\\QT\\Tools\\mingw810_32\\i686-w64-mingw32\\include","-fmessage-length=0","-fdiagnostics-show-note-include-stack","-fretain-comments-from-system-headers","-fmacro-backtrace-limit=0","-ferror-limit=1000","-x","c++","D:\\Desktop\\631\\firmware\\firmwareUpgrade\\main.cpp"],"directory":"D:/Desktop/631/firmware/build-firmwareUpgrade-Desktop_Qt_5_15_2_MinGW_32_bit-Debug/.qtc_clangd","file":"D:/Desktop/631/firmware/firmwareUpgrade/main.cpp"},{"arguments":["clang","-Wno-documentation-unknown-command","-Wno-unknown-warning-option","-Wno-unknown-pragmas","-nostdinc","-nostdinc++","-g","-std=gnu++11","-Wall","-Wextra","-Wextra","-fexceptions","-mthreads","-fsyntax-only","-m32","--target=i686-w64-mingw32","-DUNICODE","-D_UNICODE","-DWIN32","-DMINGW_HAS_SECURE_API","-DQT_DEPRECATED_WARNINGS","-DQT_QML_DEBUG","-DQT_NETWORK_LIB","-DQT_CORE_LIB","-DQ_CREATOR_RUN","-DQT_ANNOTATE_FUNCTION(x)=__attribute__((annotate(#x)))","-IF:\\QT\\Tools\\QtCreator\\share\\qtcreator\\cplusplus\\wrappedMingwHeaders","-IF:\\QT\\Tools\\QtCreator\\share\\qtcreator\\cplusplus\\wrappedQtHeaders","-IF:\\QT\\Tools\\QtCreator\\share\\qtcreator\\cplusplus\\wrappedQtHeaders\\QtCore","-ID:\\Desktop\\631\\firmware\\firmwareUpgrade","-IF:\\QT\\5.15.2\\mingw81_32\\include","-IF:\\QT\\5.15.2\\mingw81_32\\include\\QtNetwork","-IF:\\QT\\5.15.2\\mingw81_32\\include\\QtCore","-ID:\\Desktop\\631\\firmware\\build-firmwareUpgrade-Desktop_Qt_5_15_2_MinGW_32_bit-Debug\\debug","-ID:\\Desktop\\631\\firmware\\build-firmwareUpgrade-Desktop_Qt_5_15_2_MinGW_32_bit-Debug","-IF:\\QT\\5.15.2\\mingw81_32\\mkspecs\\win32-g++","-isystem","F:\\QT\\Tools\\mingw810_32\\lib\\gcc\\i686-w64-mingw32\\8.1.0\\include\\c++","-isystem","F:\\QT\\Tools\\mingw810_32\\lib\\gcc\\i686-w64-mingw32\\8.1.0\\include\\c++\\i686-w64-mingw32","-isystem","F:\\QT\\Tools\\mingw810_32\\lib\\gcc\\i686-w64-mingw32\\8.1.0\\include\\c++\\backward","-isystem","F:\\QT\\Tools\\QtCreator\\bin\\clang\\lib\\clang\\16\\include","-isystem","F:\\QT\\Tools\\mingw810_32\\i686-w64-mingw32\\include","-fmessage-length=0","-fdiagnostics-show-note-include-stack","-fretain-comments-from-system-headers","-fmacro-backtrace-limit=0","-ferror-limit=1000","-x","c++","D:\\Desktop\\631\\firmware\\firmwareUpgrade\\protocal\\utility.cpp"],"directory":"D:/Desktop/631/firmware/build-firmwareUpgrade-Desktop_Qt_5_15_2_MinGW_32_bit-Debug/.qtc_clangd","file":"D:/Desktop/631/firmware/firmwareUpgrade/protocal/utility.cpp"},{"arguments":["clang","-Wno-documentation-unknown-command","-Wno-unknown-warning-option","-Wno-unknown-pragmas","-nostdinc","-nostdinc++","-g","-std=gnu++11","-Wall","-Wextra","-Wextra","-fexceptions","-mthreads","-fsyntax-only","-m32","--target=i686-w64-mingw32","-DUNICODE","-D_UNICODE","-DWIN32","-DMINGW_HAS_SECURE_API","-DQT_DEPRECATED_WARNINGS","-DQT_QML_DEBUG","-DQT_NETWORK_LIB","-DQT_CORE_LIB","-DQ_CREATOR_RUN","-DQT_ANNOTATE_FUNCTION(x)=__attribute__((annotate(#x)))","-IF:\\QT\\Tools\\QtCreator\\share\\qtcreator\\cplusplus\\wrappedMingwHeaders","-IF:\\QT\\Tools\\QtCreator\\share\\qtcreator\\cplusplus\\wrappedQtHeaders","-IF:\\QT\\Tools\\QtCreator\\share\\qtcreator\\cplusplus\\wrappedQtHeaders\\QtCore","-ID:\\Desktop\\631\\firmware\\firmwareUpgrade","-IF:\\QT\\5.15.2\\mingw81_32\\include","-IF:\\QT\\5.15.2\\mingw81_32\\include\\QtNetwork","-IF:\\QT\\5.15.2\\mingw81_32\\include\\QtCore","-ID:\\Desktop\\631\\firmware\\build-firmwareUpgrade-Desktop_Qt_5_15_2_MinGW_32_bit-Debug\\debug","-ID:\\Desktop\\631\\firmware\\build-firmwareUpgrade-Desktop_Qt_5_15_2_MinGW_32_bit-Debug","-IF:\\QT\\5.15.2\\mingw81_32\\mkspecs\\win32-g++","-isystem","F:\\QT\\Tools\\mingw810_32\\lib\\gcc\\i686-w64-mingw32\\8.1.0\\include\\c++","-isystem","F:\\QT\\Tools\\mingw810_32\\lib\\gcc\\i686-w64-mingw32\\8.1.0\\include\\c++\\i686-w64-mingw32","-isystem","F:\\QT\\Tools\\mingw810_32\\lib\\gcc\\i686-w64-mingw32\\8.1.0\\include\\c++\\backward","-isystem","F:\\QT\\Tools\\QtCreator\\bin\\clang\\lib\\clang\\16\\include","-isystem","F:\\QT\\Tools\\mingw810_32\\i686-w64-mingw32\\include","-fmessage-length=0","-fdiagnostics-show-note-include-stack","-fretain-comments-from-system-headers","-fmacro-backtrace-limit=0","-ferror-limit=1000","-x","c++","D:\\Desktop\\631\\firmware\\firmwareUpgrade\\tftp\\tftp.cpp"],"directory":"D:/Desktop/631/firmware/build-firmwareUpgrade-Desktop_Qt_5_15_2_MinGW_32_bit-Debug/.qtc_clangd","file":"D:/Desktop/631/firmware/firmwareUpgrade/tftp/tftp.cpp"},{"arguments":["clang","-Wno-documentation-unknown-command","-Wno-unknown-warning-option","-Wno-unknown-pragmas","-nostdinc","-nostdinc++","-g","-std=gnu++11","-Wall","-Wextra","-Wextra","-fexceptions","-mthreads","-fsyntax-only","-m32","--target=i686-w64-mingw32","-DUNICODE","-D_UNICODE","-DWIN32","-DMINGW_HAS_SECURE_API","-DQT_DEPRECATED_WARNINGS","-DQT_QML_DEBUG","-DQT_NETWORK_LIB","-DQT_CORE_LIB","-DQ_CREATOR_RUN","-DQT_ANNOTATE_FUNCTION(x)=__attribute__((annotate(#x)))","-IF:\\QT\\Tools\\QtCreator\\share\\qtcreator\\cplusplus\\wrappedMingwHeaders","-IF:\\QT\\Tools\\QtCreator\\share\\qtcreator\\cplusplus\\wrappedQtHeaders","-IF:\\QT\\Tools\\QtCreator\\share\\qtcreator\\cplusplus\\wrappedQtHeaders\\QtCore","-ID:\\Desktop\\631\\firmware\\firmwareUpgrade","-IF:\\QT\\5.15.2\\mingw81_32\\include","-IF:\\QT\\5.15.2\\mingw81_32\\include\\QtNetwork","-IF:\\QT\\5.15.2\\mingw81_32\\include\\QtCore","-ID:\\Desktop\\631\\firmware\\build-firmwareUpgrade-Desktop_Qt_5_15_2_MinGW_32_bit-Debug\\debug","-ID:\\Desktop\\631\\firmware\\build-firmwareUpgrade-Desktop_Qt_5_15_2_MinGW_32_bit-Debug","-IF:\\QT\\5.15.2\\mingw81_32\\mkspecs\\win32-g++","-isystem","F:\\QT\\Tools\\mingw810_32\\lib\\gcc\\i686-w64-mingw32\\8.1.0\\include\\c++","-isystem","F:\\QT\\Tools\\mingw810_32\\lib\\gcc\\i686-w64-mingw32\\8.1.0\\include\\c++\\i686-w64-mingw32","-isystem","F:\\QT\\Tools\\mingw810_32\\lib\\gcc\\i686-w64-mingw32\\8.1.0\\include\\c++\\backward","-isystem","F:\\QT\\Tools\\QtCreator\\bin\\clang\\lib\\clang\\16\\include","-isystem","F:\\QT\\Tools\\mingw810_32\\i686-w64-mingw32\\include","-fmessage-length=0","-fdiagnostics-show-note-include-stack","-fretain-comments-from-system-headers","-fmacro-backtrace-limit=0","-ferror-limit=1000","-x","c++","D:\\Desktop\\631\\firmware\\firmwareUpgrade\\thread\\thread.cpp"],"directory":"D:/Desktop/631/firmware/build-firmwareUpgrade-Desktop_Qt_5_15_2_MinGW_32_bit-Debug/.qtc_clangd","file":"D:/Desktop/631/firmware/firmwareUpgrade/thread/thread.cpp"},{"arguments":["clang","-Wno-documentation-unknown-command","-Wno-unknown-warning-option","-Wno-unknown-pragmas","-nostdinc","-nostdinc++","-g","-std=gnu++11","-Wall","-Wextra","-Wextra","-fexceptions","-mthreads","-fsyntax-only","-m32","--target=i686-w64-mingw32","-DUNICODE","-D_UNICODE","-DWIN32","-DMINGW_HAS_SECURE_API","-DQT_DEPRECATED_WARNINGS","-DQT_QML_DEBUG","-DQT_NETWORK_LIB","-DQT_CORE_LIB","-DQ_CREATOR_RUN","-DQT_ANNOTATE_FUNCTION(x)=__attribute__((annotate(#x)))","-IF:\\QT\\Tools\\QtCreator\\share\\qtcreator\\cplusplus\\wrappedMingwHeaders","-IF:\\QT\\Tools\\QtCreator\\share\\qtcreator\\cplusplus\\wrappedQtHeaders","-IF:\\QT\\Tools\\QtCreator\\share\\qtcreator\\cplusplus\\wrappedQtHeaders\\QtCore","-ID:\\Desktop\\631\\firmware\\firmwareUpgrade","-IF:\\QT\\5.15.2\\mingw81_32\\include","-IF:\\QT\\5.15.2\\mingw81_32\\include\\QtNetwork","-IF:\\QT\\5.15.2\\mingw81_32\\include\\QtCore","-ID:\\Desktop\\631\\firmware\\build-firmwareUpgrade-Desktop_Qt_5_15_2_MinGW_32_bit-Debug\\debug","-ID:\\Desktop\\631\\firmware\\build-firmwareUpgrade-Desktop_Qt_5_15_2_MinGW_32_bit-Debug","-IF:\\QT\\5.15.2\\mingw81_32\\mkspecs\\win32-g++","-isystem","F:\\QT\\Tools\\mingw810_32\\lib\\gcc\\i686-w64-mingw32\\8.1.0\\include\\c++","-isystem","F:\\QT\\Tools\\mingw810_32\\lib\\gcc\\i686-w64-mingw32\\8.1.0\\include\\c++\\i686-w64-mingw32","-isystem","F:\\QT\\Tools\\mingw810_32\\lib\\gcc\\i686-w64-mingw32\\8.1.0\\include\\c++\\backward","-isystem","F:\\QT\\Tools\\QtCreator\\bin\\clang\\lib\\clang\\16\\include","-isystem","F:\\QT\\Tools\\mingw810_32\\i686-w64-mingw32\\include","-fmessage-length=0","-fdiagnostics-show-note-include-stack","-fretain-comments-from-system-headers","-fmacro-backtrace-limit=0","-ferror-limit=1000","-x","c++","D:\\Desktop\\631\\firmware\\firmwareUpgrade\\thread\\uploadthread.cpp"],"directory":"D:/Desktop/631/firmware/build-firmwareUpgrade-Desktop_Qt_5_15_2_MinGW_32_bit-Debug/.qtc_clangd","file":"D:/Desktop/631/firmware/firmwareUpgrade/thread/uploadthread.cpp"},{"arguments":["clang","-Wno-documentation-unknown-command","-Wno-unknown-warning-option","-Wno-unknown-pragmas","-nostdinc","-nostdinc++","-g","-std=gnu++11","-Wall","-Wextra","-Wextra","-fexceptions","-mthreads","-fsyntax-only","-m32","--target=i686-w64-mingw32","-DUNICODE","-D_UNICODE","-DWIN32","-DMINGW_HAS_SECURE_API","-DQT_DEPRECATED_WARNINGS","-DQT_QML_DEBUG","-DQT_NETWORK_LIB","-DQT_CORE_LIB","-DQ_CREATOR_RUN","-DQT_ANNOTATE_FUNCTION(x)=__attribute__((annotate(#x)))","-IF:\\QT\\Tools\\QtCreator\\share\\qtcreator\\cplusplus\\wrappedMingwHeaders","-IF:\\QT\\Tools\\QtCreator\\share\\qtcreator\\cplusplus\\wrappedQtHeaders","-IF:\\QT\\Tools\\QtCreator\\share\\qtcreator\\cplusplus\\wrappedQtHeaders\\QtCore","-ID:\\Desktop\\631\\firmware\\firmwareUpgrade","-IF:\\QT\\5.15.2\\mingw81_32\\include","-IF:\\QT\\5.15.2\\mingw81_32\\include\\QtNetwork","-IF:\\QT\\5.15.2\\mingw81_32\\include\\QtCore","-ID:\\Desktop\\631\\firmware\\build-firmwareUpgrade-Desktop_Qt_5_15_2_MinGW_32_bit-Debug\\debug","-ID:\\Desktop\\631\\firmware\\build-firmwareUpgrade-Desktop_Qt_5_15_2_MinGW_32_bit-Debug","-IF:\\QT\\5.15.2\\mingw81_32\\mkspecs\\win32-g++","-isystem","F:\\QT\\Tools\\mingw810_32\\lib\\gcc\\i686-w64-mingw32\\8.1.0\\include\\c++","-isystem","F:\\QT\\Tools\\mingw810_32\\lib\\gcc\\i686-w64-mingw32\\8.1.0\\include\\c++\\i686-w64-mingw32","-isystem","F:\\QT\\Tools\\mingw810_32\\lib\\gcc\\i686-w64-mingw32\\8.1.0\\include\\c++\\backward","-isystem","F:\\QT\\Tools\\QtCreator\\bin\\clang\\lib\\clang\\16\\include","-isystem","F:\\QT\\Tools\\mingw810_32\\i686-w64-mingw32\\include","-fmessage-length=0","-fdiagnostics-show-note-include-stack","-fretain-comments-from-system-headers","-fmacro-backtrace-limit=0","-ferror-limit=1000","-x","c++-header","D:\\Desktop\\631\\firmware\\firmwareUpgrade\\crc\\crc.h"],"directory":"D:/Desktop/631/firmware/build-firmwareUpgrade-Desktop_Qt_5_15_2_MinGW_32_bit-Debug/.qtc_clangd","file":"D:/Desktop/631/firmware/firmwareUpgrade/crc/crc.h"},{"arguments":["clang","-Wno-documentation-unknown-command","-Wno-unknown-warning-option","-Wno-unknown-pragmas","-nostdinc","-nostdinc++","-g","-std=gnu++11","-Wall","-Wextra","-Wextra","-fexceptions","-mthreads","-fsyntax-only","-m32","--target=i686-w64-mingw32","-DUNICODE","-D_UNICODE","-DWIN32","-DMINGW_HAS_SECURE_API","-DQT_DEPRECATED_WARNINGS","-DQT_QML_DEBUG","-DQT_NETWORK_LIB","-DQT_CORE_LIB","-DQ_CREATOR_RUN","-DQT_ANNOTATE_FUNCTION(x)=__attribute__((annotate(#x)))","-IF:\\QT\\Tools\\QtCreator\\share\\qtcreator\\cplusplus\\wrappedMingwHeaders","-IF:\\QT\\Tools\\QtCreator\\share\\qtcreator\\cplusplus\\wrappedQtHeaders","-IF:\\QT\\Tools\\QtCreator\\share\\qtcreator\\cplusplus\\wrappedQtHeaders\\QtCore","-ID:\\Desktop\\631\\firmware\\firmwareUpgrade","-IF:\\QT\\5.15.2\\mingw81_32\\include","-IF:\\QT\\5.15.2\\mingw81_32\\include\\QtNetwork","-IF:\\QT\\5.15.2\\mingw81_32\\include\\QtCore","-ID:\\Desktop\\631\\firmware\\build-firmwareUpgrade-Desktop_Qt_5_15_2_MinGW_32_bit-Debug\\debug","-ID:\\Desktop\\631\\firmware\\build-firmwareUpgrade-Desktop_Qt_5_15_2_MinGW_32_bit-Debug","-IF:\\QT\\5.15.2\\mingw81_32\\mkspecs\\win32-g++","-isystem","F:\\QT\\Tools\\mingw810_32\\lib\\gcc\\i686-w64-mingw32\\8.1.0\\include\\c++","-isystem","F:\\QT\\Tools\\mingw810_32\\lib\\gcc\\i686-w64-mingw32\\8.1.0\\include\\c++\\i686-w64-mingw32","-isystem","F:\\QT\\Tools\\mingw810_32\\lib\\gcc\\i686-w64-mingw32\\8.1.0\\include\\c++\\backward","-isystem","F:\\QT\\Tools\\QtCreator\\bin\\clang\\lib\\clang\\16\\include","-isystem","F:\\QT\\Tools\\mingw810_32\\i686-w64-mingw32\\include","-fmessage-length=0","-fdiagnostics-show-note-include-stack","-fretain-comments-from-system-headers","-fmacro-backtrace-limit=0","-ferror-limit=1000","-x","c++-header","D:\\Desktop\\631\\firmware\\firmwareUpgrade\\device\\device.h"],"directory":"D:/Desktop/631/firmware/build-firmwareUpgrade-Desktop_Qt_5_15_2_MinGW_32_bit-Debug/.qtc_clangd","file":"D:/Desktop/631/firmware/firmwareUpgrade/device/device.h"},{"arguments":["clang","-Wno-documentation-unknown-command","-Wno-unknown-warning-option","-Wno-unknown-pragmas","-nostdinc","-nostdinc++","-g","-std=gnu++11","-Wall","-Wextra","-Wextra","-fexceptions","-mthreads","-fsyntax-only","-m32","--target=i686-w64-mingw32","-DUNICODE","-D_UNICODE","-DWIN32","-DMINGW_HAS_SECURE_API","-DQT_DEPRECATED_WARNINGS","-DQT_QML_DEBUG","-DQT_NETWORK_LIB","-DQT_CORE_LIB","-DQ_CREATOR_RUN","-DQT_ANNOTATE_FUNCTION(x)=__attribute__((annotate(#x)))","-IF:\\QT\\Tools\\QtCreator\\share\\qtcreator\\cplusplus\\wrappedMingwHeaders","-IF:\\QT\\Tools\\QtCreator\\share\\qtcreator\\cplusplus\\wrappedQtHeaders","-IF:\\QT\\Tools\\QtCreator\\share\\qtcreator\\cplusplus\\wrappedQtHeaders\\QtCore","-ID:\\Desktop\\631\\firmware\\firmwareUpgrade","-IF:\\QT\\5.15.2\\mingw81_32\\include","-IF:\\QT\\5.15.2\\mingw81_32\\include\\QtNetwork","-IF:\\QT\\5.15.2\\mingw81_32\\include\\QtCore","-ID:\\Desktop\\631\\firmware\\build-firmwareUpgrade-Desktop_Qt_5_15_2_MinGW_32_bit-Debug\\debug","-ID:\\Desktop\\631\\firmware\\build-firmwareUpgrade-Desktop_Qt_5_15_2_MinGW_32_bit-Debug","-IF:\\QT\\5.15.2\\mingw81_32\\mkspecs\\win32-g++","-isystem","F:\\QT\\Tools\\mingw810_32\\lib\\gcc\\i686-w64-mingw32\\8.1.0\\include\\c++","-isystem","F:\\QT\\Tools\\mingw810_32\\lib\\gcc\\i686-w64-mingw32\\8.1.0\\include\\c++\\i686-w64-mingw32","-isystem","F:\\QT\\Tools\\mingw810_32\\lib\\gcc\\i686-w64-mingw32\\8.1.0\\include\\c++\\backward","-isystem","F:\\QT\\Tools\\QtCreator\\bin\\clang\\lib\\clang\\16\\include","-isystem","F:\\QT\\Tools\\mingw810_32\\i686-w64-mingw32\\include","-fmessage-length=0","-fdiagnostics-show-note-include-stack","-fretain-comments-from-system-headers","-fmacro-backtrace-limit=0","-ferror-limit=1000","-x","c++-header","D:\\Desktop\\631\\firmware\\firmwareUpgrade\\dir.h"],"directory":"D:/Desktop/631/firmware/build-firmwareUpgrade-Desktop_Qt_5_15_2_MinGW_32_bit-Debug/.qtc_clangd","file":"D:/Desktop/631/firmware/firmwareUpgrade/dir.h"},{"arguments":["clang","-Wno-documentation-unknown-command","-Wno-unknown-warning-option","-Wno-unknown-pragmas","-nostdinc","-nostdinc++","-g","-std=gnu++11","-Wall","-Wextra","-Wextra","-fexceptions","-mthreads","-fsyntax-only","-m32","--target=i686-w64-mingw32","-DUNICODE","-D_UNICODE","-DWIN32","-DMINGW_HAS_SECURE_API","-DQT_DEPRECATED_WARNINGS","-DQT_QML_DEBUG","-DQT_NETWORK_LIB","-DQT_CORE_LIB","-DQ_CREATOR_RUN","-DQT_ANNOTATE_FUNCTION(x)=__attribute__((annotate(#x)))","-IF:\\QT\\Tools\\QtCreator\\share\\qtcreator\\cplusplus\\wrappedMingwHeaders","-IF:\\QT\\Tools\\QtCreator\\share\\qtcreator\\cplusplus\\wrappedQtHeaders","-IF:\\QT\\Tools\\QtCreator\\share\\qtcreator\\cplusplus\\wrappedQtHeaders\\QtCore","-ID:\\Desktop\\631\\firmware\\firmwareUpgrade","-IF:\\QT\\5.15.2\\mingw81_32\\include","-IF:\\QT\\5.15.2\\mingw81_32\\include\\QtNetwork","-IF:\\QT\\5.15.2\\mingw81_32\\include\\QtCore","-ID:\\Desktop\\631\\firmware\\build-firmwareUpgrade-Desktop_Qt_5_15_2_MinGW_32_bit-Debug\\debug","-ID:\\Desktop\\631\\firmware\\build-firmwareUpgrade-Desktop_Qt_5_15_2_MinGW_32_bit-Debug","-IF:\\QT\\5.15.2\\mingw81_32\\mkspecs\\win32-g++","-isystem","F:\\QT\\Tools\\mingw810_32\\lib\\gcc\\i686-w64-mingw32\\8.1.0\\include\\c++","-isystem","F:\\QT\\Tools\\mingw810_32\\lib\\gcc\\i686-w64-mingw32\\8.1.0\\include\\c++\\i686-w64-mingw32","-isystem","F:\\QT\\Tools\\mingw810_32\\lib\\gcc\\i686-w64-mingw32\\8.1.0\\include\\c++\\backward","-isystem","F:\\QT\\Tools\\QtCreator\\bin\\clang\\lib\\clang\\16\\include","-isystem","F:\\QT\\Tools\\mingw810_32\\i686-w64-mingw32\\include","-fmessage-length=0","-fdiagnostics-show-note-include-stack","-fretain-comments-from-system-headers","-fmacro-backtrace-limit=0","-ferror-limit=1000","-x","c++-header","D:\\Desktop\\631\\firmware\\firmwareUpgrade\\firmwareupgrade.h"],"directory":"D:/Desktop/631/firmware/build-firmwareUpgrade-Desktop_Qt_5_15_2_MinGW_32_bit-Debug/.qtc_clangd","file":"D:/Desktop/631/firmware/firmwareUpgrade/firmwareupgrade.h"},{"arguments":["clang","-Wno-documentation-unknown-command","-Wno-unknown-warning-option","-Wno-unknown-pragmas","-nostdinc","-nostdinc++","-g","-std=gnu++11","-Wall","-Wextra","-Wextra","-fexceptions","-mthreads","-fsyntax-only","-m32","--target=i686-w64-mingw32","-DUNICODE","-D_UNICODE","-DWIN32","-DMINGW_HAS_SECURE_API","-DQT_DEPRECATED_WARNINGS","-DQT_QML_DEBUG","-DQT_NETWORK_LIB","-DQT_CORE_LIB","-DQ_CREATOR_RUN","-DQT_ANNOTATE_FUNCTION(x)=__attribute__((annotate(#x)))","-IF:\\QT\\Tools\\QtCreator\\share\\qtcreator\\cplusplus\\wrappedMingwHeaders","-IF:\\QT\\Tools\\QtCreator\\share\\qtcreator\\cplusplus\\wrappedQtHeaders","-IF:\\QT\\Tools\\QtCreator\\share\\qtcreator\\cplusplus\\wrappedQtHeaders\\QtCore","-ID:\\Desktop\\631\\firmware\\firmwareUpgrade","-IF:\\QT\\5.15.2\\mingw81_32\\include","-IF:\\QT\\5.15.2\\mingw81_32\\include\\QtNetwork","-IF:\\QT\\5.15.2\\mingw81_32\\include\\QtCore","-ID:\\Desktop\\631\\firmware\\build-firmwareUpgrade-Desktop_Qt_5_15_2_MinGW_32_bit-Debug\\debug","-ID:\\Desktop\\631\\firmware\\build-firmwareUpgrade-Desktop_Qt_5_15_2_MinGW_32_bit-Debug","-IF:\\QT\\5.15.2\\mingw81_32\\mkspecs\\win32-g++","-isystem","F:\\QT\\Tools\\mingw810_32\\lib\\gcc\\i686-w64-mingw32\\8.1.0\\include\\c++","-isystem","F:\\QT\\Tools\\mingw810_32\\lib\\gcc\\i686-w64-mingw32\\8.1.0\\include\\c++\\i686-w64-mingw32","-isystem","F:\\QT\\Tools\\mingw810_32\\lib\\gcc\\i686-w64-mingw32\\8.1.0\\include\\c++\\backward","-isystem","F:\\QT\\Tools\\QtCreator\\bin\\clang\\lib\\clang\\16\\include","-isystem","F:\\QT\\Tools\\mingw810_32\\i686-w64-mingw32\\include","-fmessage-length=0","-fdiagnostics-show-note-include-stack","-fretain-comments-from-system-headers","-fmacro-backtrace-limit=0","-ferror-limit=1000","-x","c++-header","D:\\Desktop\\631\\firmware\\firmwareUpgrade\\protocal\\protocal.h"],"directory":"D:/Desktop/631/firmware/build-firmwareUpgrade-Desktop_Qt_5_15_2_MinGW_32_bit-Debug/.qtc_clangd","file":"D:/Desktop/631/firmware/firmwareUpgrade/protocal/protocal.h"},{"arguments":["clang","-Wno-documentation-unknown-command","-Wno-unknown-warning-option","-Wno-unknown-pragmas","-nostdinc","-nostdinc++","-g","-std=gnu++11","-Wall","-Wextra","-Wextra","-fexceptions","-mthreads","-fsyntax-only","-m32","--target=i686-w64-mingw32","-DUNICODE","-D_UNICODE","-DWIN32","-DMINGW_HAS_SECURE_API","-DQT_DEPRECATED_WARNINGS","-DQT_QML_DEBUG","-DQT_NETWORK_LIB","-DQT_CORE_LIB","-DQ_CREATOR_RUN","-DQT_ANNOTATE_FUNCTION(x)=__attribute__((annotate(#x)))","-IF:\\QT\\Tools\\QtCreator\\share\\qtcreator\\cplusplus\\wrappedMingwHeaders","-IF:\\QT\\Tools\\QtCreator\\share\\qtcreator\\cplusplus\\wrappedQtHeaders","-IF:\\QT\\Tools\\QtCreator\\share\\qtcreator\\cplusplus\\wrappedQtHeaders\\QtCore","-ID:\\Desktop\\631\\firmware\\firmwareUpgrade","-IF:\\QT\\5.15.2\\mingw81_32\\include","-IF:\\QT\\5.15.2\\mingw81_32\\include\\QtNetwork","-IF:\\QT\\5.15.2\\mingw81_32\\include\\QtCore","-ID:\\Desktop\\631\\firmware\\build-firmwareUpgrade-Desktop_Qt_5_15_2_MinGW_32_bit-Debug\\debug","-ID:\\Desktop\\631\\firmware\\build-firmwareUpgrade-Desktop_Qt_5_15_2_MinGW_32_bit-Debug","-IF:\\QT\\5.15.2\\mingw81_32\\mkspecs\\win32-g++","-isystem","F:\\QT\\Tools\\mingw810_32\\lib\\gcc\\i686-w64-mingw32\\8.1.0\\include\\c++","-isystem","F:\\QT\\Tools\\mingw810_32\\lib\\gcc\\i686-w64-mingw32\\8.1.0\\include\\c++\\i686-w64-mingw32","-isystem","F:\\QT\\Tools\\mingw810_32\\lib\\gcc\\i686-w64-mingw32\\8.1.0\\include\\c++\\backward","-isystem","F:\\QT\\Tools\\QtCreator\\bin\\clang\\lib\\clang\\16\\include","-isystem","F:\\QT\\Tools\\mingw810_32\\i686-w64-mingw32\\include","-fmessage-length=0","-fdiagnostics-show-note-include-stack","-fretain-comments-from-system-headers","-fmacro-backtrace-limit=0","-ferror-limit=1000","-x","c++-header","D:\\Desktop\\631\\firmware\\firmwareUpgrade\\protocal\\utility.h"],"directory":"D:/Desktop/631/firmware/build-firmwareUpgrade-Desktop_Qt_5_15_2_MinGW_32_bit-Debug/.qtc_clangd","file":"D:/Desktop/631/firmware/firmwareUpgrade/protocal/utility.h"},{"arguments":["clang","-Wno-documentation-unknown-command","-Wno-unknown-warning-option","-Wno-unknown-pragmas","-nostdinc","-nostdinc++","-g","-std=gnu++11","-Wall","-Wextra","-Wextra","-fexceptions","-mthreads","-fsyntax-only","-m32","--target=i686-w64-mingw32","-DUNICODE","-D_UNICODE","-DWIN32","-DMINGW_HAS_SECURE_API","-DQT_DEPRECATED_WARNINGS","-DQT_QML_DEBUG","-DQT_NETWORK_LIB","-DQT_CORE_LIB","-DQ_CREATOR_RUN","-DQT_ANNOTATE_FUNCTION(x)=__attribute__((annotate(#x)))","-IF:\\QT\\Tools\\QtCreator\\share\\qtcreator\\cplusplus\\wrappedMingwHeaders","-IF:\\QT\\Tools\\QtCreator\\share\\qtcreator\\cplusplus\\wrappedQtHeaders","-IF:\\QT\\Tools\\QtCreator\\share\\qtcreator\\cplusplus\\wrappedQtHeaders\\QtCore","-ID:\\Desktop\\631\\firmware\\firmwareUpgrade","-IF:\\QT\\5.15.2\\mingw81_32\\include","-IF:\\QT\\5.15.2\\mingw81_32\\include\\QtNetwork","-IF:\\QT\\5.15.2\\mingw81_32\\include\\QtCore","-ID:\\Desktop\\631\\firmware\\build-firmwareUpgrade-Desktop_Qt_5_15_2_MinGW_32_bit-Debug\\debug","-ID:\\Desktop\\631\\firmware\\build-firmwareUpgrade-Desktop_Qt_5_15_2_MinGW_32_bit-Debug","-IF:\\QT\\5.15.2\\mingw81_32\\mkspecs\\win32-g++","-isystem","F:\\QT\\Tools\\mingw810_32\\lib\\gcc\\i686-w64-mingw32\\8.1.0\\include\\c++","-isystem","F:\\QT\\Tools\\mingw810_32\\lib\\gcc\\i686-w64-mingw32\\8.1.0\\include\\c++\\i686-w64-mingw32","-isystem","F:\\QT\\Tools\\mingw810_32\\lib\\gcc\\i686-w64-mingw32\\8.1.0\\include\\c++\\backward","-isystem","F:\\QT\\Tools\\QtCreator\\bin\\clang\\lib\\clang\\16\\include","-isystem","F:\\QT\\Tools\\mingw810_32\\i686-w64-mingw32\\include","-fmessage-length=0","-fdiagnostics-show-note-include-stack","-fretain-comments-from-system-headers","-fmacro-backtrace-limit=0","-ferror-limit=1000","-x","c++-header","D:\\Desktop\\631\\firmware\\firmwareUpgrade\\singleton\\singleton.h"],"directory":"D:/Desktop/631/firmware/build-firmwareUpgrade-Desktop_Qt_5_15_2_MinGW_32_bit-Debug/.qtc_clangd","file":"D:/Desktop/631/firmware/firmwareUpgrade/singleton/singleton.h"},{"arguments":["clang","-Wno-documentation-unknown-command","-Wno-unknown-warning-option","-Wno-unknown-pragmas","-nostdinc","-nostdinc++","-g","-std=gnu++11","-Wall","-Wextra","-Wextra","-fexceptions","-mthreads","-fsyntax-only","-m32","--target=i686-w64-mingw32","-DUNICODE","-D_UNICODE","-DWIN32","-DMINGW_HAS_SECURE_API","-DQT_DEPRECATED_WARNINGS","-DQT_QML_DEBUG","-DQT_NETWORK_LIB","-DQT_CORE_LIB","-DQ_CREATOR_RUN","-DQT_ANNOTATE_FUNCTION(x)=__attribute__((annotate(#x)))","-IF:\\QT\\Tools\\QtCreator\\share\\qtcreator\\cplusplus\\wrappedMingwHeaders","-IF:\\QT\\Tools\\QtCreator\\share\\qtcreator\\cplusplus\\wrappedQtHeaders","-IF:\\QT\\Tools\\QtCreator\\share\\qtcreator\\cplusplus\\wrappedQtHeaders\\QtCore","-ID:\\Desktop\\631\\firmware\\firmwareUpgrade","-IF:\\QT\\5.15.2\\mingw81_32\\include","-IF:\\QT\\5.15.2\\mingw81_32\\include\\QtNetwork","-IF:\\QT\\5.15.2\\mingw81_32\\include\\QtCore","-ID:\\Desktop\\631\\firmware\\build-firmwareUpgrade-Desktop_Qt_5_15_2_MinGW_32_bit-Debug\\debug","-ID:\\Desktop\\631\\firmware\\build-firmwareUpgrade-Desktop_Qt_5_15_2_MinGW_32_bit-Debug","-IF:\\QT\\5.15.2\\mingw81_32\\mkspecs\\win32-g++","-isystem","F:\\QT\\Tools\\mingw810_32\\lib\\gcc\\i686-w64-mingw32\\8.1.0\\include\\c++","-isystem","F:\\QT\\Tools\\mingw810_32\\lib\\gcc\\i686-w64-mingw32\\8.1.0\\include\\c++\\i686-w64-mingw32","-isystem","F:\\QT\\Tools\\mingw810_32\\lib\\gcc\\i686-w64-mingw32\\8.1.0\\include\\c++\\backward","-isystem","F:\\QT\\Tools\\QtCreator\\bin\\clang\\lib\\clang\\16\\include","-isystem","F:\\QT\\Tools\\mingw810_32\\i686-w64-mingw32\\include","-fmessage-length=0","-fdiagnostics-show-note-include-stack","-fretain-comments-from-system-headers","-fmacro-backtrace-limit=0","-ferror-limit=1000","-x","c++-header","D:\\Desktop\\631\\firmware\\firmwareUpgrade\\tftp\\tftp.h"],"directory":"D:/Desktop/631/firmware/build-firmwareUpgrade-Desktop_Qt_5_15_2_MinGW_32_bit-Debug/.qtc_clangd","file":"D:/Desktop/631/firmware/firmwareUpgrade/tftp/tftp.h"},{"arguments":["clang","-Wno-documentation-unknown-command","-Wno-unknown-warning-option","-Wno-unknown-pragmas","-nostdinc","-nostdinc++","-g","-std=gnu++11","-Wall","-Wextra","-Wextra","-fexceptions","-mthreads","-fsyntax-only","-m32","--target=i686-w64-mingw32","-DUNICODE","-D_UNICODE","-DWIN32","-DMINGW_HAS_SECURE_API","-DQT_DEPRECATED_WARNINGS","-DQT_QML_DEBUG","-DQT_NETWORK_LIB","-DQT_CORE_LIB","-DQ_CREATOR_RUN","-DQT_ANNOTATE_FUNCTION(x)=__attribute__((annotate(#x)))","-IF:\\QT\\Tools\\QtCreator\\share\\qtcreator\\cplusplus\\wrappedMingwHeaders","-IF:\\QT\\Tools\\QtCreator\\share\\qtcreator\\cplusplus\\wrappedQtHeaders","-IF:\\QT\\Tools\\QtCreator\\share\\qtcreator\\cplusplus\\wrappedQtHeaders\\QtCore","-ID:\\Desktop\\631\\firmware\\firmwareUpgrade","-IF:\\QT\\5.15.2\\mingw81_32\\include","-IF:\\QT\\5.15.2\\mingw81_32\\include\\QtNetwork","-IF:\\QT\\5.15.2\\mingw81_32\\include\\QtCore","-ID:\\Desktop\\631\\firmware\\build-firmwareUpgrade-Desktop_Qt_5_15_2_MinGW_32_bit-Debug\\debug","-ID:\\Desktop\\631\\firmware\\build-firmwareUpgrade-Desktop_Qt_5_15_2_MinGW_32_bit-Debug","-IF:\\QT\\5.15.2\\mingw81_32\\mkspecs\\win32-g++","-isystem","F:\\QT\\Tools\\mingw810_32\\lib\\gcc\\i686-w64-mingw32\\8.1.0\\include\\c++","-isystem","F:\\QT\\Tools\\mingw810_32\\lib\\gcc\\i686-w64-mingw32\\8.1.0\\include\\c++\\i686-w64-mingw32","-isystem","F:\\QT\\Tools\\mingw810_32\\lib\\gcc\\i686-w64-mingw32\\8.1.0\\include\\c++\\backward","-isystem","F:\\QT\\Tools\\QtCreator\\bin\\clang\\lib\\clang\\16\\include","-isystem","F:\\QT\\Tools\\mingw810_32\\i686-w64-mingw32\\include","-fmessage-length=0","-fdiagnostics-show-note-include-stack","-fretain-comments-from-system-headers","-fmacro-backtrace-limit=0","-ferror-limit=1000","-x","c++-header","D:\\Desktop\\631\\firmware\\firmwareUpgrade\\tftp\\tftprequest.h"],"directory":"D:/Desktop/631/firmware/build-firmwareUpgrade-Desktop_Qt_5_15_2_MinGW_32_bit-Debug/.qtc_clangd","file":"D:/Desktop/631/firmware/firmwareUpgrade/tftp/tftprequest.h"},{"arguments":["clang","-Wno-documentation-unknown-command","-Wno-unknown-warning-option","-Wno-unknown-pragmas","-nostdinc","-nostdinc++","-g","-std=gnu++11","-Wall","-Wextra","-Wextra","-fexceptions","-mthreads","-fsyntax-only","-m32","--target=i686-w64-mingw32","-DUNICODE","-D_UNICODE","-DWIN32","-DMINGW_HAS_SECURE_API","-DQT_DEPRECATED_WARNINGS","-DQT_QML_DEBUG","-DQT_NETWORK_LIB","-DQT_CORE_LIB","-DQ_CREATOR_RUN","-DQT_ANNOTATE_FUNCTION(x)=__attribute__((annotate(#x)))","-IF:\\QT\\Tools\\QtCreator\\share\\qtcreator\\cplusplus\\wrappedMingwHeaders","-IF:\\QT\\Tools\\QtCreator\\share\\qtcreator\\cplusplus\\wrappedQtHeaders","-IF:\\QT\\Tools\\QtCreator\\share\\qtcreator\\cplusplus\\wrappedQtHeaders\\QtCore","-ID:\\Desktop\\631\\firmware\\firmwareUpgrade","-IF:\\QT\\5.15.2\\mingw81_32\\include","-IF:\\QT\\5.15.2\\mingw81_32\\include\\QtNetwork","-IF:\\QT\\5.15.2\\mingw81_32\\include\\QtCore","-ID:\\Desktop\\631\\firmware\\build-firmwareUpgrade-Desktop_Qt_5_15_2_MinGW_32_bit-Debug\\debug","-ID:\\Desktop\\631\\firmware\\build-firmwareUpgrade-Desktop_Qt_5_15_2_MinGW_32_bit-Debug","-IF:\\QT\\5.15.2\\mingw81_32\\mkspecs\\win32-g++","-isystem","F:\\QT\\Tools\\mingw810_32\\lib\\gcc\\i686-w64-mingw32\\8.1.0\\include\\c++","-isystem","F:\\QT\\Tools\\mingw810_32\\lib\\gcc\\i686-w64-mingw32\\8.1.0\\include\\c++\\i686-w64-mingw32","-isystem","F:\\QT\\Tools\\mingw810_32\\lib\\gcc\\i686-w64-mingw32\\8.1.0\\include\\c++\\backward","-isystem","F:\\QT\\Tools\\QtCreator\\bin\\clang\\lib\\clang\\16\\include","-isystem","F:\\QT\\Tools\\mingw810_32\\i686-w64-mingw32\\include","-fmessage-length=0","-fdiagnostics-show-note-include-stack","-fretain-comments-from-system-headers","-fmacro-backtrace-limit=0","-ferror-limit=1000","-x","c++-header","D:\\Desktop\\631\\firmware\\firmwareUpgrade\\thread\\thread.h"],"directory":"D:/Desktop/631/firmware/build-firmwareUpgrade-Desktop_Qt_5_15_2_MinGW_32_bit-Debug/.qtc_clangd","file":"D:/Desktop/631/firmware/firmwareUpgrade/thread/thread.h"},{"arguments":["clang","-Wno-documentation-unknown-command","-Wno-unknown-warning-option","-Wno-unknown-pragmas","-nostdinc","-nostdinc++","-g","-std=gnu++11","-Wall","-Wextra","-Wextra","-fexceptions","-mthreads","-fsyntax-only","-m32","--target=i686-w64-mingw32","-DUNICODE","-D_UNICODE","-DWIN32","-DMINGW_HAS_SECURE_API","-DQT_DEPRECATED_WARNINGS","-DQT_QML_DEBUG","-DQT_NETWORK_LIB","-DQT_CORE_LIB","-DQ_CREATOR_RUN","-DQT_ANNOTATE_FUNCTION(x)=__attribute__((annotate(#x)))","-IF:\\QT\\Tools\\QtCreator\\share\\qtcreator\\cplusplus\\wrappedMingwHeaders","-IF:\\QT\\Tools\\QtCreator\\share\\qtcreator\\cplusplus\\wrappedQtHeaders","-IF:\\QT\\Tools\\QtCreator\\share\\qtcreator\\cplusplus\\wrappedQtHeaders\\QtCore","-ID:\\Desktop\\631\\firmware\\firmwareUpgrade","-IF:\\QT\\5.15.2\\mingw81_32\\include","-IF:\\QT\\5.15.2\\mingw81_32\\include\\QtNetwork","-IF:\\QT\\5.15.2\\mingw81_32\\include\\QtCore","-ID:\\Desktop\\631\\firmware\\build-firmwareUpgrade-Desktop_Qt_5_15_2_MinGW_32_bit-Debug\\debug","-ID:\\Desktop\\631\\firmware\\build-firmwareUpgrade-Desktop_Qt_5_15_2_MinGW_32_bit-Debug","-IF:\\QT\\5.15.2\\mingw81_32\\mkspecs\\win32-g++","-isystem","F:\\QT\\Tools\\mingw810_32\\lib\\gcc\\i686-w64-mingw32\\8.1.0\\include\\c++","-isystem","F:\\QT\\Tools\\mingw810_32\\lib\\gcc\\i686-w64-mingw32\\8.1.0\\include\\c++\\i686-w64-mingw32","-isystem","F:\\QT\\Tools\\mingw810_32\\lib\\gcc\\i686-w64-mingw32\\8.1.0\\include\\c++\\backward","-isystem","F:\\QT\\Tools\\QtCreator\\bin\\clang\\lib\\clang\\16\\include","-isystem","F:\\QT\\Tools\\mingw810_32\\i686-w64-mingw32\\include","-fmessage-length=0","-fdiagnostics-show-note-include-stack","-fretain-comments-from-system-headers","-fmacro-backtrace-limit=0","-ferror-limit=1000","-x","c++-header","D:\\Desktop\\631\\firmware\\firmwareUpgrade\\thread\\uploadthread.h"],"directory":"D:/Desktop/631/firmware/build-firmwareUpgrade-Desktop_Qt_5_15_2_MinGW_32_bit-Debug/.qtc_clangd","file":"D:/Desktop/631/firmware/firmwareUpgrade/thread/uploadthread.h"}]